galytics3
