Metadata-Version: 2.1
Name: galytics3
Version: 2020.10.28
Summary: Обертка над библиотекой google_api_python_client для работы с API Google Analytics v3
Home-page: https://github.com/pavelmaksimov/galytics3
Author: Pavel Maksimov
Author-email: vur21@ya.ru
License: MIT
Keywords: google,analytics,api,client,python
Platform: UNKNOWN
